odoo/addons/sm_partago_accounting/__init__.py
odoo/addons/sm_partago_accounting/__manifest__.py
odoo/addons/sm_partago_accounting/models/__init__.py
odoo/addons/sm_partago_accounting/models/models_sm_member.py
odoo/addons/sm_partago_accounting/views/views_members.xml
odoo11_addon_sm_partago_accounting-11.0.0.0.2.dist-info/METADATA
odoo11_addon_sm_partago_accounting-11.0.0.0.2.dist-info/WHEEL
odoo11_addon_sm_partago_accounting-11.0.0.0.2.dist-info/top_level.txt
odoo11_addon_sm_partago_accounting-11.0.0.0.2.dist-info/RECORD
